extra_thicc.py
extra_thicc-0.1.3.dist-info/entry_points.txt
extra_thicc-0.1.3.dist-info/LICENSE
extra_thicc-0.1.3.dist-info/METADATA
extra_thicc-0.1.3.dist-info/WHEEL
extra_thicc-0.1.3.dist-info/RECORD
