Metadata-Version: 2.3
Name: extra-thicc
Version: 0.1.3
Summary: Convert strings to 乇乂丅尺卂 丅卄工匚匚
License: MIT
Keywords: extrathicc,generator
Author: Michał Dziadowicz
Author-email: michal@dziadowicz.it
Requires-Python: >=3.11,<4.0
Classifier: Development Status :: 4 - Beta
Classifier: Environment :: Console
Classifier: License :: OSI Approved :: MIT License
Classifier: Operating System :: OS Independent
Classifier: Programming Language :: Python :: 3
Classifier: Programming Language :: Python :: 3.11
Classifier: Programming Language :: Python :: 3.12
Classifier: Programming Language :: Python :: 3.13
Classifier: Topic :: Utilities
Project-URL: Homepage, https://dziadowicz.it/
Project-URL: Repository, https://gitlab.com/mxdzi/extra-thicc
